knockprobe/Tools.py
knockprobe/__init__.py
knockprobe/core.py
knockprobe-1.0.2.data/data/LICENSE.txt
knockprobe-1.0.2.data/data/README.md
knockprobe-1.0.2.data/data/requirements.txt
knockprobe-1.0.2.data/data/requirements_test.txt
knockprobe-1.0.2.dist-info/DESCRIPTION.rst
knockprobe-1.0.2.dist-info/METADATA
knockprobe-1.0.2.dist-info/RECORD
knockprobe-1.0.2.dist-info/WHEEL
knockprobe-1.0.2.dist-info/metadata.json
knockprobe-1.0.2.dist-info/top_level.txt
