Metadata-Version: 2.0
Name: knockprobe
Version: 1.0.2
Summary: knockprobe SDK
Home-page: https://knock.center
Author: Laurent Champagnac / Laurent Labatut
Author-email: dev@knock.center
License: GNU GENERAL PUBLIC LICENSE
Requires-Dist: ujson
